{
    "projects": [
      { 
        "name": "EPNS",
        "url": "https://epns.io/",
        "description": "Blockchain based notifications that are chain agnostic, platform independent and incentivized",
        "image": "/images/projects/epns.png"
      },
      { 
        "name": "Good Ghosting",
        "url": "https://goodghosting.com/",
        "description": "A better way to grow your savings",
        "image": "/images/projects/goodghosting.png"
      },
      {
        "name": "Swivel Finance",
        "url": "https://swivel.finance/",
        "description": "The protocol for interest-rate derivatives",
        "image": "/images/projects/swivel.png" 
      },
      { 
        "name": "EthBlockArt",
        "url": "https://ethblock.art/",
        "description": "Create your own deterministic art painting Ethereum blocks, mint NFTs.",
        "image": "/images/projects/eba.jpg"
      },
      { 
        "name": "Charged Particles",
        "url": "https://www.charged.fi/",
        "description": "Now, every NFT can contain digital assets",
        "image": "/images/projects/charged_particles.png"
      },
      { 
        "name": "Nifty Ink",
        "url": "https://nifty.ink/",
        "description": "Instantly onboarding artists: no downloads, no onramps",
        "image": "/images/projects/nifty_ink.png"
      },
      { 
        "name": "Parcel",
        "url": "https://parcel.money/",
        "description": "Treasury Management, simplified for DAOs",
        "image": "/images/projects/parcel.png"
      },
      { 
        "name": "Akropolis",
        "url": "https://www.akropolis.io/",
        "description": "Earn DeFi yield on autopilot",
        "image": "/images/projects/akropolis.png"
      }
    ]
  }